[
    {
        "name": "Cry.For.The.Bad.Man.2019.1080p.BluRay.H264.AAC-RARBG",
        "language": "English",
        "poster_link": "https://m.media-amazon.com/images/M/MV5BOTE2MTMwMzEtYjhlMy00MjFjLWI5MDItMTU5M2MwNWY5NmEwXkEyXkFqcGdeQXVyMjczOTE1OTQ@._V1_.jpg",
        "genres": "Thriller,Horror,",
        "id": "8110000",
        "search_results": []
    },
    {
        "name": "People.Presents.Harry.and.Meghans.American.Dream.2021.1080p.WEB.h264-BAE",
        "language": "English",
        "poster_link": "https://images-na.ssl-images-amazon.com/images/I/61ZYf7b266L._AC_SY741_.jpg",
        "genres": "",
        "id": "14117316",
        "search_results": []
    },
    {
        "name": "Sunshine.Follows.Rain.1946.SWEDISH.1080p.NF.WEBRip.DDP2.0.x264-PAAI",
        "language": "Swedish",
        "poster_link": "https://m.media-amazon.com/images/M/MV5BYWYwNWNlYjAtZGRlYy00MzdlLWIwMzktYWVhZTFlMjFhYWFlXkEyXkFqcGdeQXVyMzg1ODEwNQ@@._V1_.jpg",
        "genres": "Romance,Drama,",
        "id": "0038497",
        "search_results": []
    },
    {
        "name": "Sara.Learns.Manners.1937.SWEDISH.1080p.NF.WEBRip.DDP2.0.x264-PAAI",
        "language": "Swedish",
        "poster_link": "https://m.media-amazon.com/images/M/MV5BODk0ZGI0NmQtOGY2OS00OWU0LWE3MmMtOGY4YjVjNmI5ZDM3XkEyXkFqcGdeQXVyMjUyNDk2ODc@._V1_.jpg",
        "genres": "Comedy,",
        "id": "0029515",
        "search_results": []
    },
    {
        "name": "Ride.Tonight.1942.SWEDISH.1080p.NF.WEBRip.DDP2.0.x264-PAAI",
        "language": "Swedish",
        "poster_link": "https://m.media-amazon.com/images/M/MV5BNjE5N2M4ZDEtODExNC00NTE3LWI1YzgtYjM0MmNiYzlhZjk5L2ltYWdlXkEyXkFqcGdeQXVyMjUyNDk2ODc@._V1_.jpg",
        "genres": "History,Drama,",
        "id": "0035251",
        "search_results": []
    },
    {
        "name": "Peas.And.Whiskers.1986.SWEDISH.1080p.NF.WEBRip.DDP2.0.x264-PAAI",
        "language": "Swedish",
        "poster_link": "https://m.media-amazon.com/images/M/MV5BYjc4NTdiNjktMDA3Ni00ODMxLWE3Y2UtNmNiYzk4ZjYxOWFjXkEyXkFqcGdeQXVyMjUyNDk2ODc@._V1_.jpg",
        "genres": "Comedy,",
        "id": "0091555",
        "search_results": []
    }
]